dashboard_lint/__init__.py
dashboard_lint/cli.py
dashboard_lint/config.py
dashboard_lint/esql_helpers.py
dashboard_lint/registry.py
dashboard_lint/rules/__init__.py
dashboard_lint/rules/chart/__init__.py
dashboard_lint/rules/chart/datatable_row_density.py
dashboard_lint/rules/chart/dimension_missing_label.py
dashboard_lint/rules/chart/esql_dimension_missing_label.py
dashboard_lint/rules/chart/esql_dynamic_time_bucket.py
dashboard_lint/rules/chart/esql_field_escaping.py
dashboard_lint/rules/chart/esql_group_by_syntax.py
dashboard_lint/rules/chart/esql_metric_missing_label.py
dashboard_lint/rules/chart/esql_missing_limit.py
dashboard_lint/rules/chart/esql_missing_sort_after_bucket.py
dashboard_lint/rules/chart/esql_sql_syntax.py
dashboard_lint/rules/chart/esql_where_clause.py
dashboard_lint/rules/chart/gauge_goal_without_max.py
dashboard_lint/rules/chart/metric_multiple_metrics_width.py
dashboard_lint/rules/chart/metric_redundant_label.py
dashboard_lint/rules/chart/narrow_xy_chart_side_legend.py
dashboard_lint/rules/chart/panel_height_for_content.py
dashboard_lint/rules/chart/pie_chart_dimension_count.py
dashboard_lint/rules/chart/pie_missing_limit.py
dashboard_lint/rules/core/__init__.py
dashboard_lint/rules/core/base.py
dashboard_lint/rules/core/decorators.py
dashboard_lint/rules/dashboard/__init__.py
dashboard_lint/rules/dashboard/dashboard_dataset_filter.py
dashboard_lint/rules/dashboard/dashboard_missing_description.py
dashboard_lint/rules/dashboard/datatable_at_bottom.py
dashboard_lint/rules/dashboard/markdown_at_top.py
dashboard_lint/rules/dashboard/metric_excessive_count.py
dashboard_lint/rules/panel/__init__.py
dashboard_lint/rules/panel/markdown_header_height.py
dashboard_lint/rules/panel/panel_description_recommended.py
dashboard_lint/rules/panel/panel_min_width.py
dashboard_lint/rules/panel/panel_title_redundant_prefix.py
dashboard_lint/runner.py
dashboard_lint/types.py
dashboard_lint/yaml_position_resolver.py
kb_dashboard_lint-0.2.7.dist-info/WHEEL
kb_dashboard_lint-0.2.7.dist-info/entry_points.txt
kb_dashboard_lint-0.2.7.dist-info/METADATA
kb_dashboard_lint-0.2.7.dist-info/RECORD
