Metadata-Version: 2.3
Name: kb-dashboard-lint
Version: 0.2.7
Summary: Linting rules for dashboard YAML configurations
License: MIT
Classifier: Development Status :: 3 - Alpha
Classifier: Intended Audience :: Developers
Classifier: License :: OSI Approved :: MIT License
Classifier: Programming Language :: Python :: 3
Classifier: Programming Language :: Python :: 3.12
Classifier: Topic :: Software Development :: Quality Assurance
Requires-Dist: kb-dashboard-core==0.2.7
Requires-Dist: pydantic>=2.12
Requires-Dist: beartype>=0.22
Requires-Dist: click>=8.3
Requires-Dist: rich-click>=1.9.0
Requires-Dist: pyyaml>=6.0.3
Requires-Dist: ruamel-yaml>=0.18.0
Requires-Python: >=3.12
